<?xml version="1.0" encoding="utf-8"?>
<annotation>
<folder>images</folder>
<filename>a62ccf6a-pos-42.png</filename>
<source>
<database>MyDatabase</database>
<annotation>COCO2017</annotation>
<image>flickr</image>
<flickrid>NULL</flickrid>
<annotator>1</annotator>
</source>
<owner>
<flickrid>NULL</flickrid>
<name>Label Studio</name>
</owner>
<size>
<width>520</width>
<height>345</height>
<depth>3</depth>
</size>
<segmented>0</segmented>
<object>
<name>Tree</name>
<pose>Unspecified</pose>
<truncated>0</truncated>
<difficult>0</difficult>
<bndbox>
<xmin>340</xmin>
<ymin>37</ymin>
<xmax>410</xmax>
<ymax>214</ymax>
</bndbox>
</object>
<object>
<name>Tree</name>
<pose>Unspecified</pose>
<truncated>0</truncated>
<difficult>0</difficult>
<bndbox>
<xmin>85</xmin>
<ymin>66</ymin>
<xmax>165</xmax>
<ymax>229</ymax>
</bndbox>
</object>
<object>
<name>Tree</name>
<pose>Unspecified</pose>
<truncated>0</truncated>
<difficult>0</difficult>
<bndbox>
<xmin>164</xmin>
<ymin>37</ymin>
<xmax>209</xmax>
<ymax>187</ymax>
</bndbox>
</object>
<object>
<name>Tree</name>
<pose>Unspecified</pose>
<truncated>0</truncated>
<difficult>0</difficult>
<bndbox>
<xmin>197</xmin>
<ymin>3</ymin>
<xmax>238</xmax>
<ymax>90</ymax>
</bndbox>
</object>
</annotation>
